clutchGen/__main__.py
clutchGen/configs.py
clutchGen/constants.py
clutchGen/enums.py
clutchGen/file_parser.py
clutchGen/generator.py
clutchGen/handlers/__init__.py
clutchGen/handlers/create_template.py
clutchGen/handlers/delete_template.py
clutchGen/handlers/edit_template.py
clutchGen/handlers/generate_project.py
clutchGen/handlers/list_templates.py
clutchGen/handlers/template_info.py
clutchGen/models.py
clutchGen/render_context.py
clutchGen/templates/constants.py.mako
clutchGen/templates/init.py.mako
clutchGen/templates/main.py.mako
clutchGen/templates/models-base.py.mako
clutchGen/templates/router.py.mako
clutchGen/templates/settings.py.mako
clutchGen/templates.ini
clutchGen/templating.py
clutchGen/utils.py
clutchgen-0.2.0.dist-info/entry_points.txt
clutchgen-0.2.0.dist-info/METADATA
clutchgen-0.2.0.dist-info/WHEEL
clutchgen-0.2.0.dist-info/RECORD
